appias/__init__.py
appias/__version__.py
appias/core.py
appias/frame.py
appias/series.py
appias/util.py
appias-0.1.1.dist-info/DESCRIPTION.rst
appias-0.1.1.dist-info/METADATA
appias-0.1.1.dist-info/RECORD
appias-0.1.1.dist-info/WHEEL
appias-0.1.1.dist-info/metadata.json
appias-0.1.1.dist-info/top_level.txt
