Metadata-Version: 2.0
Name: appias
Version: 0.1.1
Summary: Machine learning workflow toolkit
Home-page: https://github.com/aglove2189/appias
Author: Aaron Glover
Author-email: aglove2189@gmail.com
License: GPL
Keywords: machine learning,data science,pandas,sklearn
Platform: Linux
Platform: OS-X
Platform: Windows
Classifier: Programming Language :: Python :: 3
Classifier: License :: OSI Approved :: GNU General Public License v3 (GPLv3)
Classifier: Operating System :: OS Independent
Requires-Dist: pandas
Requires-Dist: numpy
Requires-Dist: scikit-learn
Requires-Dist: matplotlib
Requires-Dist: seaborn
Requires-Dist: tqdm
